{
    "BatchObjs": [
        {
            "JsonData": {
                "ObjectTag": "Left_0",
                "Prototype_GameObject": "Prototype_StoryTrigger\u0000",
                "QuestIndex": -1,
                "RigidBody": {
                    "ColliderType": 5,
                    "Density": 10.0,
                    "OriginTransform": [
                        20.0,
                        0.0,
                        0.0,
                        0.0,
                        0.0,
                        10.0,
                        0.0,
                        0.0,
                        0.0,
                        0.0,
                        1.0,
                        0.0,
                        0.0,
                        0.0,
                        0.0,
                        1.0
                    ],
                    "ShapeType": 0,
                    "bKinematic": false,
                    "bTrigger": true
                },
                "Talk": false,
                "TalkIndex": [
                    71,
                    72
                ],
                "Transform": {
                    "WorldMatrix": [
                        9.099629210140847e-07,
                        1.6560627652192905e-12,
                        -1.0,
                        0.0,
                        0.0,
                        0.9999984502792358,
                        1.6560601631340766e-12,
                        0.0,
                        1.0,
                        0.0,
                        9.099629210140847e-07,
                        0.0,
                        -22.04320526123047,
                        4.824442386627197,
                        -2.778862476348877,
                        1.0
                    ]
                }
            },
            "Preset": {
                "JsonPath": "",
                "Layer": "Layer_Trigger",
                "ProtoTag": "Prototype_StoryTrigger"
            },
            "WorldMatrix": [
                9.099629210140847e-07,
                1.6560627652192905e-12,
                -1.0,
                0.0,
                0.0,
                0.9999984502792358,
                1.6560601631340766e-12,
                0.0,
                1.0,
                0.0,
                9.099629210140847e-07,
                0.0,
                -22.04320526123047,
                4.824442386627197,
                -2.778862476348877,
                1.0
            ]
        },
        {
            "JsonData": {
                "ObjectTag": "Left_1",
                "Prototype_GameObject": "Prototype_StoryTrigger\u0000",
                "QuestIndex": -1,
                "RigidBody": {
                    "ColliderType": 5,
                    "Density": 10.0,
                    "OriginTransform": [
                        15.0,
                        0.0,
                        0.0,
                        0.0,
                        0.0,
                        10.0,
                        0.0,
                        0.0,
                        0.0,
                        0.0,
                        1.0,
                        0.0,
                        0.0,
                        0.0,
                        0.0,
                        1.0
                    ],
                    "ShapeType": 0,
                    "bKinematic": false,
                    "bTrigger": true
                },
                "Talk": false,
                "TalkIndex": [
                    73
                ],
                "Transform": {
                    "WorldMatrix": [
                        -9.099629210140847e-07,
                        -1.6560650420438527e-12,
                        -1.0,
                        0.0,
                        0.0,
                        0.9999927878379822,
                        -1.6560531158199554e-12,
                        0.0,
                        1.0,
                        0.0,
                        -9.099629210140847e-07,
                        0.0,
                        -78.21614074707031,
                        1.139988899230957,
                        -34.150672912597656,
                        1.0
                    ]
                }
            },
            "Preset": {
                "JsonPath": "",
                "Layer": "Layer_Trigger",
                "ProtoTag": "Prototype_StoryTrigger"
            },
            "WorldMatrix": [
                -9.099629210140847e-07,
                -1.6560650420438527e-12,
                -1.0,
                0.0,
                0.0,
                0.9999927878379822,
                -1.6560531158199554e-12,
                0.0,
                1.0,
                0.0,
                -9.099629210140847e-07,
                0.0,
                -78.21614074707031,
                1.139988899230957,
                -34.150672912597656,
                1.0
            ]
        },
        {
            "JsonData": {
                "ObjectTag": "Left_2",
                "Prototype_GameObject": "Prototype_StoryTrigger\u0000",
                "QuestIndex": -1,
                "RigidBody": {
                    "ColliderType": 5,
                    "Density": 10.0,
                    "OriginTransform": [
                        10.0,
                        0.0,
                        0.0,
                        0.0,
                        0.0,
                        10.0,
                        0.0,
                        0.0,
                        0.0,
                        0.0,
                        5.0,
                        0.0,
                        0.0,
                        0.0,
                        0.0,
                        1.0
                    ],
                    "ShapeType": 0,
                    "bKinematic": false,
                    "bTrigger": true
                },
                "Talk": false,
                "TalkIndex": [
                    74
                ],
                "Transform": {
                    "WorldMatrix": [
                        1.0,
                        0.0,
                        0.0,
                        0.0,
                        0.0,
                        1.0,
                        0.0,
                        0.0,
                        0.0,
                        0.0,
                        1.0,
                        0.0,
                        -68.50371551513672,
                        1.1398546695709229,
                        -11.081779479980469,
                        1.0
                    ]
                }
            },
            "Preset": {
                "JsonPath": "",
                "Layer": "Layer_Trigger",
                "ProtoTag": "Prototype_StoryTrigger"
            },
            "WorldMatrix": [
                1.0,
                0.0,
                0.0,
                0.0,
                0.0,
                1.0,
                0.0,
                0.0,
                0.0,
                0.0,
                1.0,
                0.0,
                -68.50371551513672,
                1.1398546695709229,
                -11.081779479980469,
                1.0
            ]
        },
        {
            "JsonData": {
                "ObjectTag": "Left_3",
                "Prototype_GameObject": "Prototype_StoryTrigger\u0000",
                "QuestIndex": -1,
                "RigidBody": {
                    "ColliderType": 5,
                    "Density": 10.0,
                    "OriginTransform": [
                        10.0,
                        0.0,
                        0.0,
                        0.0,
                        0.0,
                        10.0,
                        0.0,
                        0.0,
                        0.0,
                        0.0,
                        10.0,
                        0.0,
                        0.0,
                        0.0,
                        0.0,
                        1.0
                    ],
                    "ShapeType": 0,
                    "bKinematic": false,
                    "bTrigger": true
                },
                "Talk": false,
                "TalkIndex": [
                    75
                ],
                "Transform": {
                    "WorldMatrix": [
                        1.0,
                        0.0,
                        0.0,
                        0.0,
                        0.0,
                        1.0,
                        0.0,
                        0.0,
                        0.0,
                        0.0,
                        1.0,
                        0.0,
                        -125.19465637207031,
                        1.1399946212768555,
                        -15.068536758422852,
                        1.0
                    ]
                }
            },
            "Preset": {
                "JsonPath": "",
                "Layer": "Layer_Trigger",
                "ProtoTag": "Prototype_StoryTrigger"
            },
            "WorldMatrix": [
                1.0,
                0.0,
                0.0,
                0.0,
                0.0,
                1.0,
                0.0,
                0.0,
                0.0,
                0.0,
                1.0,
                0.0,
                -125.19465637207031,
                1.1399946212768555,
                -15.068536758422852,
                1.0
            ]
        },
        {
            "JsonData": {
                "ObjectTag": "Left_4",
                "Prototype_GameObject": "Prototype_StoryTrigger\u0000",
                "QuestIndex": -1,
                "RigidBody": {
                    "ColliderType": 5,
                    "Density": 10.0,
                    "OriginTransform": [
                        20.0,
                        0.0,
                        0.0,
                        0.0,
                        0.0,
                        10.0,
                        0.0,
                        0.0,
                        0.0,
                        0.0,
                        1.0,
                        0.0,
                        0.0,
                        0.0,
                        0.0,
                        1.0
                    ],
                    "ShapeType": 0,
                    "bKinematic": false,
                    "bTrigger": true
                },
                "Talk": false,
                "TalkIndex": [
                    76,
                    77,
                    78
                ],
                "Transform": {
                    "WorldMatrix": [
                        1.0,
                        0.0,
                        0.0,
                        0.0,
                        0.0,
                        1.0,
                        0.0,
                        0.0,
                        0.0,
                        0.0,
                        1.0,
                        0.0,
                        -136.67454528808594,
                        1.1399987936019897,
                        10.602831840515137,
                        1.0
                    ]
                }
            },
            "Preset": {
                "JsonPath": "",
                "Layer": "Layer_Trigger",
                "ProtoTag": "Prototype_StoryTrigger"
            },
            "WorldMatrix": [
                1.0,
                0.0,
                0.0,
                0.0,
                0.0,
                1.0,
                0.0,
                0.0,
                0.0,
                0.0,
                1.0,
                0.0,
                -136.67454528808594,
                1.1399987936019897,
                10.602831840515137,
                1.0
            ]
        },
        {
            "JsonData": {
                "ObjectTag": "Left_5",
                "Prototype_GameObject": "Prototype_StoryTrigger\u0000",
                "QuestIndex": -1,
                "RigidBody": {
                    "ColliderType": 5,
                    "Density": 10.0,
                    "OriginTransform": [
                        15.0,
                        0.0,
                        0.0,
                        0.0,
                        0.0,
                        10.0,
                        0.0,
                        0.0,
                        0.0,
                        0.0,
                        1.0,
                        0.0,
                        0.0,
                        0.0,
                        0.0,
                        1.0
                    ],
                    "ShapeType": 0,
                    "bKinematic": false,
                    "bTrigger": true
                },
                "Talk": false,
                "TalkIndex": [
                    79
                ],
                "Transform": {
                    "WorldMatrix": [
                        1.9470718370939721e-07,
                        1.686653881881675e-13,
                        -1.0,
                        0.0,
                        0.0,
                        0.9999995231628418,
                        1.6866530687300457e-13,
                        0.0,
                        1.0,
                        0.0,
                        1.9470718370939721e-07,
                        0.0,
                        -167.37026977539063,
                        -7.660021781921387,
                        46.02069854736328,
                        1.0
                    ]
                }
            },
            "Preset": {
                "JsonPath": "",
                "Layer": "Layer_Trigger",
                "ProtoTag": "Prototype_StoryTrigger"
            },
            "WorldMatrix": [
                1.9470718370939721e-07,
                1.686653881881675e-13,
                -1.0,
                0.0,
                0.0,
                0.9999995231628418,
                1.6866530687300457e-13,
                0.0,
                1.0,
                0.0,
                1.9470718370939721e-07,
                0.0,
                -167.37026977539063,
                -7.660021781921387,
                46.02069854736328,
                1.0
            ]
        }
    ]
}