{"BillBoardType":0,"BufferProtoTag":"Prototype_Component_VIBuffer_Rect","Children":[[1.0,0.0,0.0,0.0,0.0,1.0,0.0,0.0,0.0,0.0,1.0,0.0,0.0,0.0,0.0,1.0]],"ModelFolderDir":"","ModelProtoTag":"../Bin/Resources/Meshes/VFX_Ver2/VFX_Ver2_em0220_Boom.static_model","ShaderParams":{"Float2s":[],"Float4s":[[0.7432788014411926,0.1527973711490631,0.14975349605083466,1.0664442777633667],[0.696969211101532,0.14327740669250488,0.14042317867279053,1.0]],"Float4x4s":[],"Floats":[3.5205419063568115],"Ints":[],"Pass":18,"Textures":["..\\Bin\\Resources\\Texture\\VFX\\T_em0220_Body_ALB.png\u0000","..\\Bin\\Resources\\Texture\\VFX\\T_em0220_Body_NML.png\u0000","..\\Bin\\Resources\\Texture\\VFX\\T_em0220_Body_RMA.png\u0000"]},"ShaderProtoTag":"Prototype_Component_Shader_VtxModel_VFX","bBillBoard":false,"bDecal":false,"bModelSprite":false,"bNormal":true,"bUseDepth":false}