{"BillBoardType":0,"BufferProtoTag":"Prototype_Component_VIBuffer_Cube","Children":[[1.0,0.0,0.0,0.0,0.0,1.0,0.0,0.0,0.0,0.0,1.0,0.0,0.0,0.0,0.0,1.0]],"ModelFolderDir":"","ModelProtoTag":"","ShaderParams":{"Float2s":[],"Float4s":[[0.08129432797431946,0.15462076663970947,0.06408335268497467,1.0]],"Float4x4s":[],"Floats":[0.43299999833106995,0.0,0.3700000047683716],"Ints":[1],"Pass":2,"Textures":["..\\Bin\\Resources\\Texture\\VFX\\T_ef_anm_aur_007.png\u0000","..\\Bin\\Resources\\Texture\\VFX\\T_ef_one_aur_001_002.png\u0000"]},"ShaderProtoTag":"Prototype_Component_Shader_VtxCube_SSDecal","bBillBoard":false,"bDecal":true,"bModelSprite":false,"bNormal":false,"bUseDepth":true}