{"ObjectTag":"","Particles":[{"ObjectTag":"Red_Rose_Particle","ParticleDirectory":"../Bin/Resources/VFX/ParticleSystem/Red_Rose_Particle.json"},{"ObjectTag":"Green_Rose_Particle","ParticleDirectory":"../Bin/Resources/VFX/ParticleSystem/Green_Rose_Particle.json"},{"ObjectTag":"WhiteRose_Particle","ParticleDirectory":"../Bin/Resources/VFX/ParticleSystem/WhiteRose_Particle.json"}],"Prototype_GameObject":"ProtoVFX_ParticleGroup\u0000","Transform":{"WorldMatrix":[1.0,0.0,0.0,0.0,0.0,1.0,0.0,0.0,0.0,0.0,1.0,0.0,0.0,0.0,0.0,1.0]}}